{
  "criteria": {
    "diorite": {
      "trigger": "minecraft:inventory_changed",
      "conditions": {
        "items": [
          {
            "items": ["minecraft:diorite"],
            "count": {
              "min": 1
            }
          }
        ]
      }
    },
    "stick": {
      "trigger": "minecraft:inventory_changed",
      "conditions": {
        "items": [
          {
            "items": ["minecraft:stick"],
            "count":{
              "min": 2
            }
          }
        ]
      }
    }
  },  
  "rewards":{
    "recipes": ["whw_recipe:stone_shovel"]
  },
  "requirements": [
    [
      "diorite",
      "stick"
    ]
  ]
}